{
    "file": "0x42db5bfe8828f12f164586af8a992b3a7b038164.sol",
    "global_structs": [
        {
            "name": "struct_block",
            "fields": {
                "coinbase": [
                    "integer"
                ],
                "difficulty": [
                    "integer"
                ],
                "gaslimit": [
                    "integer"
                ],
                "number": [
                    "integer"
                ],
                "timestamp": [
                    "integer"
                ]
            }
        },
        {
            "name": "struct_msg",
            "fields": {
                "data": [
                    "integer"
                ],
                "sender": [
                    "integer"
                ],
                "sig": [
                    "integer"
                ],
                "value": [
                    "integer"
                ]
            }
        },
        {
            "name": "struct_tx",
            "fields": {
                "gasprice": [
                    "integer"
                ],
                "origin": [
                    "integer"
                ]
            }
        },
        {
            "name": "struct_this",
            "fields": {
                "balance": [
                    "integer"
                ],
                "address": [
                    "integer"
                ]
            }
        }
    ],
    "global_variables": [
        {
            "name": "block",
            "type": [
                "struct_block"
            ],
            "init": []
        },
        {
            "name": "msg",
            "type": [
                "struct_msg"
            ],
            "init": [
                "0x1b"
            ]
        },
        {
            "name": "now",
            "type": [
                "integer"
            ],
            "init": []
        },
        {
            "name": "tx",
            "type": [
                "struct_tx"
            ],
            "init": []
        },
        {
            "name": "this",
            "type": [
                "struct_this"
            ],
            "init": [
                "0x1c"
            ]
        },
        {
            "name": "msg_sender",
            "type": [
                "integer"
            ],
            "init": [
                "0x1d"
            ]
        },
        {
            "name": "addmod",
            "type": [
                "function3"
            ],
            "init": []
        },
        {
            "name": "mulmod",
            "type": [
                "function3"
            ],
            "init": []
        },
        {
            "name": "keccak",
            "type": [
                "function1"
            ],
            "init": []
        },
        {
            "name": "sha256",
            "type": [
                "function1"
            ],
            "init": []
        },
        {
            "name": "sha3",
            "type": [
                "integer"
            ],
            "init": []
        },
        {
            "name": "ripemd160",
            "type": [
                "function1"
            ],
            "init": []
        },
        {
            "name": "ecrecover",
            "type": [
                "function4"
            ],
            "init": []
        },
        {
            "name": "blockhash",
            "type": [
                "function1"
            ],
            "init": []
        },
        {
            "name": "adr",
            "type": [
                "integer"
            ],
            "init": []
        },
        {
            "name": "emails",
            "type": [
                "integer"
            ],
            "init": [
                "0xa"
            ]
        },
        {
            "name": "Limit",
            "type": [
                "integer"
            ],
            "init": [
                "0x9"
            ]
        },
        {
            "name": "Owner",
            "type": [
                "integer"
            ],
            "init": [
                "0x8"
            ]
        },
        {
            "name": "firstTest",
            "type": [
                "integer"
            ],
            "init": []
        }
    ],
    "global_blocks": [
        {
            "scope": "__GLOBAL__",
            "addr": "0x8",
            "instructions": [
                "Owner = 405314233721731614567849376158975379573823696283"
            ]
        },
        {
            "scope": "__GLOBAL__",
            "addr": "0x9",
            "instructions": [
                "Limit = 1000000000000000000"
            ]
        },
        {
            "scope": "__GLOBAL__",
            "addr": "0xa",
            "instructions": [
                "emails = 216215328027251570991303672707549707894655565075"
            ]
        },
        {
            "scope": "__GLOBAL__",
            "addr": "0xc",
            "instructions": [
                "msg.sender = 0x6"
            ]
        },
        {
            "scope": "__GLOBAL__",
            "addr": "0xd",
            "instructions": [
                "this.address = 0x5"
            ]
        },
        {
            "scope": "__GLOBAL__",
            "addr": "0xe",
            "instructions": [
                "msg_sender = 0x4"
            ]
        },
        {
            "scope": "__GLOBAL__",
            "addr": "0x1b",
            "instructions": [
                "msg.sender = 0x6"
            ]
        },
        {
            "scope": "__GLOBAL__",
            "addr": "0x1c",
            "instructions": [
                "this.address = 0x5"
            ]
        },
        {
            "scope": "__GLOBAL__",
            "addr": "0x1d",
            "instructions": [
                "msg_sender = 0x4"
            ]
        }
    ],
    "range_variables": [
        {
            "name": "Limit",
            "addrs": [
                "0x2",
                "0x4"
            ]
        },
        {
            "name": "emails",
            "addrs": [
                "0x2",
                "0x6"
            ]
        },
        {
            "name": "adr",
            "addrs": [
                "0x2",
                "0x7",
                "0xb"
            ]
        }
    ],
    "range_blocks": [
        {
            "scope": "__RANGE__",
            "addr": "0x1",
            "instructions": [
                "NOP"
            ]
        },
        {
            "scope": "__RANGE__",
            "addr": "0x2",
            "instructions": [
                "NOP"
            ]
        },
        {
            "scope": "__RANGE__",
            "addr": "0x4",
            "instructions": [
                "CLR_0 = msg.sender",
                "RTMP_17 = CLR_0 == Owner",
                "CONDITION RTMP_17 0x3 0x1"
            ]
        },
        {
            "scope": "__RANGE__",
            "addr": "0x3",
            "instructions": [
                "Limit = U"
            ]
        },
        {
            "scope": "__RANGE__",
            "addr": "0x6",
            "instructions": [
                "CLR_1 = msg.sender",
                "RTMP_18 = CLR_1 == Owner",
                "CONDITION RTMP_18 0x5 0x1"
            ]
        },
        {
            "scope": "__RANGE__",
            "addr": "0x5",
            "instructions": [
                "emails = U"
            ]
        },
        {
            "scope": "__RANGE__",
            "addr": "0x7",
            "instructions": [
                "CLR_2 = msg.sender",
                "adr = CLR_2"
            ]
        },
        {
            "scope": "__RANGE__",
            "addr": "0xb",
            "instructions": [
                "CLR_3 = msg.sender",
                "adr = CLR_3"
            ]
        }
    ],
    "root_addr": "0x1e",
    "dest_addrs": [
        "0x28"
    ],
    "normal_blocks": [
        {
            "scope": "fallback",
            "addr": "0x1e",
            "instructions": [
                "NOP",
                "JUMP 0x1f"
            ]
        },
        {
            "scope": "fallback",
            "addr": "0x1f",
            "instructions": [
                "NOP",
                "JUMP 0x20"
            ]
        },
        {
            "scope": "fallback",
            "addr": "0x20",
            "instructions": [
                "CLR_4 = msg.sender",
                "adr = CLR_4",
                "CLR_5 = msg.value",
                "TMP_6 = CLR_5 > Limit",
                "CONDITION TMP_6 0x21 0x22"
            ]
        },
        {
            "scope": "fallback",
            "addr": "0x21",
            "instructions": [
                "TMP_21 = 1",
                "TMP_7 = CALL1 sha3 TMP_21",
                "TMP_8 = NEW_VAL unknown",
                "ATTACK",
                "TMP_9 = NEW_VAL boolean",
                "JUMP 0x23"
            ]
        },
        {
            "scope": "withdrawal",
            "addr": "0x23",
            "instructions": [
                "NOP",
                "JUMP 0x24"
            ]
        },
        {
            "scope": "withdrawal",
            "addr": "0x24",
            "instructions": [
                "CLR_6 = msg.sender",
                "adr = CLR_6",
                "CLR_7 = msg.value",
                "TMP_6 = CLR_7 > Limit",
                "CONDITION TMP_6 0x25 0x22"
            ]
        },
        {
            "scope": "withdrawal",
            "addr": "0x25",
            "instructions": [
                "TMP_22 = 1",
                "TMP_7 = CALL1 sha3 TMP_22",
                "TMP_8 = NEW_VAL unknown",
                "TMP_9 = NEW_VAL boolean",
                "JUMP 0x26"
            ]
        },
        {
            "scope": "withdrawal",
            "addr": "0x27",
            "instructions": [
                "NOP",
                "JUMP 0x28"
            ]
        },
        {
            "scope": "withdrawal",
            "addr": "0x26",
            "instructions": [
                "REF_2 = BALANCE this",
                "CLR_8 = this.balance",
                "WRP_0 = CLR_8 - REF_2",
                "this.balance = WRP_0",
                "TMP_10 = NEW_VAL unknown",
                "JUMP 0x27"
            ]
        },
        {
            "scope": "fallback",
            "addr": "0x28",
            "instructions": [
                "REF_2 = BALANCE this",
                "CLR_9 = this.balance",
                "WRP_1 = CLR_9 - REF_2",
                "this.balance = WRP_1",
                "TMP_10 = NEW_VAL unknown"
            ]
        },
        {
            "scope": "trap",
            "addr": "0x22",
            "instructions": [
                "NOP"
            ]
        }
    ]
}